brik/__init__.py
brik/app.py
brik/brik.py
brik/cli.py
brik/exceptions.py
brik/commands/__init__.py
brik/commands/config.py
brik/commands/git.py
brik/commands/install.py
brik/commands/make.py
brik/commands/setup.py
brik/commands/update.py
brik/commands/utils.py
brik/config/__init__.py
brik/config/common_site_config.py
brik/config/lets_encrypt.py
brik/config/nginx.py
brik/config/procfile.py
brik/config/production_setup.py
brik/config/redis.py
brik/config/site_config.py
brik/config/supervisor.py
brik/config/systemd.py
brik/config/templates/502.html
brik/config/templates/503.png
brik/config/templates/Procfile
brik/config/templates/brik_manager_nginx.conf
brik/config/templates/criscostack_sudoers
brik/config/templates/letsencrypt.cfg
brik/config/templates/nginx.conf
brik/config/templates/nginx_default.conf
brik/config/templates/redis_cache.conf
brik/config/templates/redis_queue.conf
brik/config/templates/supervisor.conf
brik/config/templates/systemd/criscostack-brik-criscostack-default-worker.service
brik/config/templates/systemd/criscostack-brik-criscostack-long-worker.service
brik/config/templates/systemd/criscostack-brik-criscostack-schedule.service
brik/config/templates/systemd/criscostack-brik-criscostack-short-worker.service
brik/config/templates/systemd/criscostack-brik-criscostack-web.service
brik/config/templates/systemd/criscostack-brik-node-socketio.service
brik/config/templates/systemd/criscostack-brik-redis-cache.service
brik/config/templates/systemd/criscostack-brik-redis-queue.service
brik/config/templates/systemd/criscostack-brik-redis.target
brik/config/templates/systemd/criscostack-brik-web.target
brik/config/templates/systemd/criscostack-brik-workers.target
brik/config/templates/systemd/criscostack-brik.target
brik/patches/__init__.py
brik/patches/patches.txt
brik/patches/v5/__init__.py
brik/patches/v5/fix_backup_cronjob.py
brik/patches/v5/fix_user_permissions.py
brik/patches/v5/set_live_reload_config.py
brik/patches/v5/update_archived_sites.py
criscostack_brik-1.0.5.dist-info/METADATA
criscostack_brik-1.0.5.dist-info/WHEEL
criscostack_brik-1.0.5.dist-info/entry_points.txt
criscostack_brik-1.0.5.dist-info/licenses/LICENSE
criscostack_brik-1.0.5.dist-info/RECORD
